aiobotocore/__init__.py
aiobotocore/_constants.py
aiobotocore/_endpoint_helpers.py
aiobotocore/_helpers.py
aiobotocore/args.py
aiobotocore/awsrequest.py
aiobotocore/client.py
aiobotocore/config.py
aiobotocore/configprovider.py
aiobotocore/context.py
aiobotocore/credentials.py
aiobotocore/discovery.py
aiobotocore/endpoint.py
aiobotocore/eventstream.py
aiobotocore/handlers.py
aiobotocore/hooks.py
aiobotocore/httpchecksum.py
aiobotocore/httpsession.py
aiobotocore/httpxsession.py
aiobotocore/paginate.py
aiobotocore/parsers.py
aiobotocore/regions.py
aiobotocore/response.py
aiobotocore/retryhandler.py
aiobotocore/session.py
aiobotocore/signers.py
aiobotocore/stub.py
aiobotocore/tokens.py
aiobotocore/utils.py
aiobotocore/waiter.py
aiobotocore/retries/__init__.py
aiobotocore/retries/adaptive.py
aiobotocore/retries/bucket.py
aiobotocore/retries/special.py
aiobotocore/retries/standard.py
aiobotocore-3.1.1.dist-info/licenses/LICENSE
aiobotocore-3.1.1.dist-info/METADATA
aiobotocore-3.1.1.dist-info/WHEEL
aiobotocore-3.1.1.dist-info/top_level.txt
aiobotocore-3.1.1.dist-info/RECORD
