Metadata-Version: 2.4
Name: aiobotocore
Version: 3.1.1
Summary: Async client for aws services using botocore and aiohttp
Author-email: Nikolay Novik <nickolainovik@gmail.com>
License-Expression: Apache-2.0
Project-URL: Repository, https://github.com/aio-libs/aiobotocore
Project-URL: Documentation, https://aiobotocore.aio-libs.org
Classifier: Development Status :: 4 - Beta
Classifier: Intended Audience :: Developers
Classifier: Intended Audience :: System Administrators
Classifier: Natural Language :: English
Classifier: Programming Language :: Python :: 3
Classifier: Programming Language :: Python :: 3.9
Classifier: Programming Language :: Python :: 3.10
Classifier: Programming Language :: Python :: 3.11
Classifier: Programming Language :: Python :: 3.12
Classifier: Programming Language :: Python :: 3.13
Classifier: Programming Language :: Python :: 3.14
Classifier: Environment :: Web Environment
Classifier: Framework :: AsyncIO
Requires-Python: >=3.9
License-File: LICENSE
Requires-Dist: aiohttp<4.0.0,>=3.12.0
Requires-Dist: aioitertools<1.0.0,>=0.5.1
Requires-Dist: botocore<1.42.31,>=1.41.0
Requires-Dist: python-dateutil<3.0.0,>=2.1
Requires-Dist: jmespath<2.0.0,>=0.7.1
Requires-Dist: multidict<7.0.0,>=6.0.0
Requires-Dist: typing-extensions<5.0.0,>=4.14.0; python_version < "3.11"
Requires-Dist: wrapt<3.0.0,>=1.10.10
Provides-Extra: httpx
Requires-Dist: httpx<0.29,>=0.25.1; extra == "httpx"
Dynamic: license-file
